focli
