Metadata-Version: 1.1
Name: focli
Version: 0.7
Summary: focli - Decent frontend to Föli stop schedules
Home-page: https://github.com/joohoi/focli
Author: Joona Hoikkala
Author-email: joona@kuori.org
License: BSD
Download-URL: https://github.com/joohoi/focli/tarball/0.7
Platform: UNKNOWN
Classifier: Programming Language :: Python
Classifier: Programming Language :: Python :: 2
Classifier: Programming Language :: Python :: 2.7
Classifier: Programming Language :: Python :: 3
Classifier: Programming Language :: Python :: 3.1
Classifier: Programming Language :: Python :: 3.2
Classifier: Programming Language :: Python :: 3.3
Classifier: Programming Language :: Python :: 3.4
Classifier: Programming Language :: Python :: 3.5
Classifier: Environment :: Console
Classifier: License :: OSI Approved :: BSD License
